snarkify_cli/__init__.py
snarkify_cli/commands/__init__.py
snarkify_cli/commands/auth.py
snarkify_cli/commands/data.py
snarkify_cli/commands/deployment.py
snarkify_cli/commands/init.py
snarkify_cli/commands/service.py
snarkify_cli/commands/shell.py
snarkify_cli/commands/task.py
snarkify_cli/commands/team.py
snarkify_cli/commands/version.py
snarkify_cli/context.py
snarkify_cli/lib/__init__.py
snarkify_cli/lib/auth.py
snarkify_cli/lib/aws_utils.py
snarkify_cli/lib/command.py
snarkify_cli/lib/configs.py
snarkify_cli/lib/constants.py
snarkify_cli/lib/docker_utils.py
snarkify_cli/lib/errors.py
snarkify_cli/lib/exception.py
snarkify_cli/lib/http_utils.py
snarkify_cli/lib/init_utils.py
snarkify_cli/lib/prompt_utils.py
snarkify_cli/lib/service_utils.py
snarkify_cli/lib/websocket_utils.py
snarkify_cli/main.py
snarkify_cli/tasks/__init__.py
snarkify_cli/tasks/constants.py
snarkify_cli/tasks/enums.py
snarkify_cli/templates/__init__.py
snarkify_cli/templates/build_templates.py
snarkify_cli/templates/rust/__init__.py
snarkify_cli/templates/rust/snarkify_template.py
snarkify_cli-0.1.7.dist-info/METADATA
snarkify_cli-0.1.7.dist-info/WHEEL
snarkify_cli-0.1.7.dist-info/entry_points.txt
snarkify_cli-0.1.7.dist-info/RECORD
